[{"tmp": "26.9", "hmt": "41.4", "time": "00:00"},{"tmp": "26.9", "hmt": "41.9", "time": "00:59"},{"tmp": "26.8", "hmt": "42.1", "time": "02:00"},{"tmp": "26.8", "hmt": "42.5", "time": "03:01"},{"tmp": "26.8", "hmt": "43.0", "time": "04:02"},{"tmp": "26.7", "hmt": "43.6", "time": "05:02"},{"tmp": "26.6", "hmt": "44.2", "time": "06:03"},{"tmp": "26.6", "hmt": "45.7", "time": "07:03"},{"tmp": "26.6", "hmt": "47.2", "time": "08:04"},{"tmp": "26.6", "hmt": "48.9", "time": "09:05"},{"tmp": "26.6", "hmt": "48.6", "time": "10:06"},{"tmp": "26.8", "hmt": "42.8", "time": "11:06"},{"tmp": "27.4", "hmt": "39.5", "time": "12:07"},{"tmp": "27.5", "hmt": "38.0", "time": "13:08"},{"tmp": "27.7", "hmt": "39.0", "time": "14:09"},{"tmp": "28.1", "hmt": "37.5", "time": "15:09"},{"tmp": "28.3", "hmt": "35.9", "time": "16:10"},{"tmp": "28.1", "hmt": "37.5", "time": "17:11"},{"tmp": "28.1", "hmt": "37.6", "time": "18:24"},{"tmp": "28.0", "hmt": "40.3", "time": "19:25"},{"tmp": "27.7", "hmt": "44.0", "time": "20:25"},{"tmp": "27.8", "hmt": "42.7", "time": "21:26"},{"tmp": "27.5", "hmt": "44.7", "time": "22:27"},{"tmp": "27.1", "hmt": "47.5", "time": "23:28"}]